killport.py
killport-1.2.0.dist-info/LICENSE
killport-1.2.0.dist-info/METADATA
killport-1.2.0.dist-info/WHEEL
killport-1.2.0.dist-info/entry_points.txt
killport-1.2.0.dist-info/top_level.txt
killport-1.2.0.dist-info/RECORD
