Metadata-Version: 2.1
Name: killport
Version: 1.2.0
Home-page: https://github.com/dannysepler/killport
Author: Danny Sepler
Author-email: dannysepler@gmail.com
License: MIT
Project-URL: Bug Tracker, https://github.com/dannysepler/killport/issues
Classifier: License :: OSI Approved :: MIT License
Classifier: Programming Language :: Python :: 3
Classifier: Programming Language :: Python :: 3 :: Only
Classifier: Programming Language :: Python :: 3.7
Classifier: Programming Language :: Python :: 3.8
Classifier: Programming Language :: Python :: 3.9
Classifier: Programming Language :: Python :: 3.10
Requires-Python: >=3.7.0
License-File: LICENSE
